{"stats":{"minecraft:used":{"minecraft:diamond_leggings":1,"minecraft:diamond_sword":13,"minecraft:air":3,"minecraft:diamond_boots":1,"minecraft:diamond_chestplate":1},"minecraft:custom":{"minecraft:time_since_rest":508,"minecraft:fall_one_cm":500,"minecraft:walk_one_cm":5118,"minecraft:total_world_time":548,"minecraft:leave_game":1,"minecraft:mob_kills":1,"minecraft:damage_taken":98,"minecraft:damage_dealt":891,"minecraft:play_time":508,"minecraft:jump":5,"minecraft:time_since_death":508},"minecraft:picked_up":{"minecraft:diamond_chestplate":1,"minecraft:tipped_arrow":4,"minecraft:diamond_sword":1,"minecraft:diamond_helmet":1,"minecraft:diamond_boots":1,"minecraft:bone":24,"minecraft:arrow":22,"minecraft:diamond_leggings":1,"minecraft:rotten_flesh":1},"minecraft:killed":{"minecraft:drowned":1}},"DataVersion":4440}